.gitignore
MANIFEST.in
README.rst
bootstrap.py
buildout.cfg
setup.py
docs/CHANGES.rst
docs/CONTRIBUTORS.rst
docs/editor.png
docs/make_translations.png
src/collective/__init__.py
src/collective.multilingualtools.egg-info/PKG-INFO
src/collective.multilingualtools.egg-info/SOURCES.txt
src/collective.multilingualtools.egg-info/dependency_links.txt
src/collective.multilingualtools.egg-info/entry_points.txt
src/collective.multilingualtools.egg-info/namespace_packages.txt
src/collective.multilingualtools.egg-info/not-zip-safe
src/collective.multilingualtools.egg-info/requires.txt
src/collective.multilingualtools.egg-info/top_level.txt
src/collective/multilingualtools/__init__.py
src/collective/multilingualtools/configure.zcml
src/collective/multilingualtools/interfaces.py
src/collective/multilingualtools/testing.py
src/collective/multilingualtools/utils.py
src/collective/multilingualtools/vocabularies.py
src/collective/multilingualtools/browser/__init__.py
src/collective/multilingualtools/browser/configure.zcml
src/collective/multilingualtools/browser/forms.py
src/collective/multilingualtools/browser/interfaces.py
src/collective/multilingualtools/browser/layout.py
src/collective/multilingualtools/browser/multilingualtools.py
src/collective/multilingualtools/browser/templates/form.pt
src/collective/multilingualtools/browser/templates/layout.pt
src/collective/multilingualtools/profiles/default/actions.xml
src/collective/multilingualtools/profiles/default/browserlayer.xml
src/collective/multilingualtools/profiles/default/cssregistry.xml
src/collective/multilingualtools/profiles/default/jsregistry.xml
src/collective/multilingualtools/profiles/default/metadata.xml
src/collective/multilingualtools/static/arrow-down.png
src/collective/multilingualtools/static/arrow.png
src/collective/multilingualtools/static/linguatools.css
src/collective/multilingualtools/static/linguatools.js
src/collective/multilingualtools/tests/__init__.py
src/collective/multilingualtools/tests/lttest.txt
src/collective/multilingualtools/tests/test_functional.py