Metadata-Version: 1.1
Name: collective.multilingualtools
Version: 0.1.1
Summary: A set of tools that simplify handling multilingual content in Plone using plone.app.multilingual.
Home-page: https://github.com/collective/collective.multilingualtools
Author: Syslab.com GmbH
Author-email: thomas@syslab.com
License: GPL
Keywords: translation multilingual internationalization
Platform: UNKNOWN
Classifier: Framework :: Plone
Classifier: Framework :: Plone :: 4.0
Classifier: Framework :: Plone :: 4.1
Classifier: Framework :: Plone :: 4.2
Classifier: Framework :: Plone :: 4.3
Classifier: Programming Language :: Python
Classifier: Topic :: Software Development :: Libraries :: Python Modules
Classifier: License :: OSI Approved :: GNU General Public License (GPL)
Classifier: License :: OSI Approved :: European Union Public Licence 1.1 (EUPL 1.1)
